<annotation>
	<folder>n03581125</folder>
	<filename>n03581125_54566</filename>
	<source>
		<database>ImageNet database</database>
	</source>
	<size>
		<width>500</width>
		<height>281</height>
		<depth>3</depth>
	</size>
	<segmented>0</segmented>
	<object>
		<name>n02958343</name>
		<pose>Unspecified</pose>
		<truncated>0</truncated>
		<difficult>0</difficult>
		<bndbox>
			<xmin>363</xmin>
			<ymin>146</ymin>
			<xmax>374</xmax>
			<ymax>157</ymax>
		</bndbox>
	</object>
	<object>
		<name>n09436708</name>
		<pose>Unspecified</pose>
		<truncated>0</truncated>
		<difficult>0</difficult>
		<bndbox>
			<xmin>0</xmin>
			<ymin>0</ymin>
			<xmax>451</xmax>
			<ymax>133</ymax>
		</bndbox>
	</object>
</annotation>